pycat/__init__.py
pycat/central_manager.py
pycat/run_pycat.py
pycat/data/__init__.py
pycat/data/data_modules.py
pycat/file_io/__init__.py
pycat/file_io/file_io.py
pycat/icons/pycat_logo-2.png
pycat/icons/pycat_logo.png
pycat/icons/pycat_logo_1024.png
pycat/icons/pycat_logo_256.png
pycat/icons/pycat_logo_512.png
pycat/toolbox/__init__.py
pycat/toolbox/correlation_func_analysis_tools.py
pycat/toolbox/data_viz_tools.py
pycat/toolbox/feature_analysis_tools.py
pycat/toolbox/image_processing_tools.py
pycat/toolbox/label_and_mask_tools.py
pycat/toolbox/layer_tools.py
pycat/toolbox/obj_based_coloc_analysis_tools.py
pycat/toolbox/pixel_wise_corr_analysis_tools.py
pycat/toolbox/segmentation_tools.py
pycat/ui/__init__.py
pycat/ui/ui_modules.py
pycat/ui/ui_utils.py
pycat/utils/__init__.py
pycat/utils/general_utils.py
pycat/utils/math_utils.py
pycat_napari-1.0.0.dist-info/METADATA
pycat_napari-1.0.0.dist-info/WHEEL
pycat_napari-1.0.0.dist-info/entry_points.txt
pycat_napari-1.0.0.dist-info/licenses/LICENSE
pycat_napari-1.0.0.dist-info/RECORD
