Metadata-Version: 2.4
Name: pycat-napari
Version: 1.0.0
Summary: Python Condensate Analysis Toolbox - A napari-based tool for biomolecular condensate analysis
Project-URL: Homepage, https://github.com/BanerjeeLab-repertoire/pycat-napari
Project-URL: Repository, https://github.com/BanerjeeLab-repertoire/pycat-napari
Project-URL: Issues, https://github.com/BanerjeeLab-repertoire/pycat-napari/issues
Author-email: Christian Neureuter <cneureut@buffalo.edu>
License: License
License-File: LICENSE
Keywords: bio-image,condensate,fluorescence,image analysis,microscopy,napari,pycat,scientific
Classifier: Development Status :: 5 - Production/Stable
Classifier: Intended Audience :: Science/Research
Classifier: License :: OSI Approved :: BSD License
Classifier: Operating System :: OS Independent
Classifier: Programming Language :: Python :: 3
Classifier: Programming Language :: Python :: 3.9
Classifier: Topic :: Scientific/Engineering :: Bio-Informatics
Classifier: Topic :: Scientific/Engineering :: Image Processing
Classifier: Topic :: Scientific/Engineering :: Visualization
Requires-Python: ==3.9.*
Requires-Dist: aicsimageio
Requires-Dist: aicspylibczi>=3.0.5
Requires-Dist: cellpose
Requires-Dist: matplotlib
Requires-Dist: napari
Requires-Dist: numpy>=1.22
Requires-Dist: opencv-python-headless
Requires-Dist: pandas
Requires-Dist: pydantic
Requires-Dist: pyqt5
Requires-Dist: pywavelets
Requires-Dist: scikit-image
Requires-Dist: scikit-learn
Requires-Dist: scipy
Requires-Dist: seaborn
Requires-Dist: simpleitk
Requires-Dist: torch
Provides-Extra: arm-mac
Requires-Dist: torch==2.1.2; (platform_system == 'Darwin' and platform_machine == 'arm64') and extra == 'arm-mac'
Requires-Dist: torchvision; (platform_system == 'Darwin' and platform_machine == 'arm64') and extra == 'arm-mac'
Provides-Extra: dev
Requires-Dist: black; extra == 'dev'
Requires-Dist: build; extra == 'dev'
Requires-Dist: pre-commit; extra == 'dev'
Requires-Dist: pytest-cov; extra == 'dev'
Requires-Dist: pytest>=7.0; extra == 'dev'
Requires-Dist: ruff; extra == 'dev'
Requires-Dist: twine; extra == 'dev'
Provides-Extra: devbio-napari
Requires-Dist: devbio-napari; extra == 'devbio-napari'
Provides-Extra: docs
Requires-Dist: myst-parser; extra == 'docs'
Requires-Dist: sphinx; extra == 'docs'
Requires-Dist: sphinx-rtd-theme; extra == 'docs'
Provides-Extra: test
Requires-Dist: pytest-cov; extra == 'test'
Requires-Dist: pytest-qt; extra == 'test'
Requires-Dist: pytest>=7.0; extra == 'test'
